challongeranking/__init__.py
challongeranking/challonge_ranking.py
challongeranking/challongeranking.py
challongeranking-0.5.dist-info/DESCRIPTION.rst
challongeranking-0.5.dist-info/METADATA
challongeranking-0.5.dist-info/RECORD
challongeranking-0.5.dist-info/WHEEL
challongeranking-0.5.dist-info/metadata.json
challongeranking-0.5.dist-info/top_level.txt
