Metadata-Version: 2.0
Name: challongeranking
Version: 0.5
Summary: Module for rating players across challonge-tournaments
Home-page: http://github.com/orouvinen/challonge-ranking
Author: Olli Rouvinen
Author-email: olli.rouvinen@gmail.com
License: MIT
Platform: UNKNOWN
Requires-Dist: pychallonge (>=1.0)
